adform/Client.py
adform/Credentials.py
odap_adform_downloader-1.0.3.dist-info/LICENSE
odap_adform_downloader-1.0.3.dist-info/WHEEL
odap_adform_downloader-1.0.3.dist-info/METADATA
odap_adform_downloader-1.0.3.dist-info/RECORD
