Metadata-Version: 2.1
Name: odap-adform-downloader
Version: 1.0.3
Summary: DataSentics adform zip downloader
Home-page: https://github.com/DataSentics/odap-adform-downloader
License: MIT
Author: Pavla
Requires-Python: >=3.7.1,<4.0.0
Classifier: License :: OSI Approved :: MIT License
Classifier: Operating System :: OS Independent
Classifier: Programming Language :: Python :: 3
Classifier: Programming Language :: Python :: 3.10
Classifier: Programming Language :: Python :: 3.8
Classifier: Programming Language :: Python :: 3.9
Requires-Dist: azure-storage-blob (>=12.8.0,<13.0.0)
Requires-Dist: requests (>=2.25.1,<3.0.0)
Project-URL: Repository, https://github.com/DataSentics/odap-adform-downloader
